{
  "TranslationProperties": {
    "Name": "server.items.Furniture_Ancient_Chest_Small.name"
  },
  "PlayerAnimationsId": "Block",
  "Categories": [
    "Furniture.Containers"
  ],
  "Set": "Furniture_Ancient",
  "Icon": "Icons/ItemsGenerated/Ancient_Capsule.png",
  "BlockType": {
    "BlockParticleSetId": "Metal",
    "BlockSoundSetId": "Metal",
    "CustomModel": "Blocks/RadioMeter/LootCapsule.blockymodel",
    "CustomModelTexture": [
      {
        "Texture": "Blocks/RadioMeter/Loot_Capsule.png",
        "Weight": 1
      }
    ],
    "DrawType": "Model",
    "Flags": {
      "IsUsable": true
    },
    "Gathering": {
      "Breaking": {
        "GatherType": "Woods"
      }
    },
    "HitboxType": "Chest_Small",
    "Material": "Solid",
    "Opacity": "Transparent",
    "ParticleColor": "#656259",
    "State": {
      "Id": "container",
      "Capacity": 9,
      "Definitions": {
        "CloseWindow": {
          "InteractionSoundEventId": "SFX_Chest_Wooden_Close",
          "CustomModelAnimation": "Blocks/Animations/LootCapsuleClose.blockyanim"
        },
        "OpenWindow": {
          "InteractionSoundEventId": "SFX_Chest_Wooden_Open",
          "CustomModelAnimation": "Blocks/Animations/LootCapsuleOpen.blockyanim"
        }
      }
    },
    "Supporting": {
      "Up": [
        {
          "FaceType": "Full"
        }
      ]
    },
    "Support": {
      "Down": [
        {
          "FaceType": "Full"
        }
      ]
    },
    "VariantRotation": "NESW",
    "Interactions": {
      "Primary": "Break_Container",
      "Use": "Open_Container"
    }
  },
  "Model": "Blocks/RadioMeter/LootCapsule.blockymodel",
  "Texture": "Blocks/RadioMeter/Loot_Capsule.png",
  "Tags": {
    "Type": [
      "Furniture"
    ],
    "Family": [
      "Ancient"
    ]
  },
  "IconProperties": {
    "Scale": 0.55,
    "Rotation": [
      22.5,
      45,
      22.5
    ],
    "Translation": [
      0,
      -15
    ]
  },
  "Recipe": {
    "Input": [
      {
        "ItemId": "Ingredient_Bar_Iron",
        "Quantity": 5
      }
    ],
    "BenchRequirement": [
      {
        "Id": "Furniture_Bench",
        "Type": "Crafting",
        "Categories": [
          "Furniture_Storage"
        ]
      }
    ],
    "RequiredMemoriesLevel": 2
  },
  "ItemSoundSetId": "ISS_Items_Metal",
  "ItemLevel": 8,
  "MaxStack": 10
}
